dump2polarion/__init__.py
dump2polarion/configuration.py
dump2polarion/csv2sqlite_cli.py
dump2polarion/csv_unicode.py
dump2polarion/dumper_cli.py
dump2polarion/exceptions.py
dump2polarion/parselogs.py
dump2polarion/polarion_tools.yaml
dump2polarion/properties.py
dump2polarion/requirements_exporter.py
dump2polarion/submit.py
dump2polarion/svn_polarion.py
dump2polarion/testcases_exporter.py
dump2polarion/transform.py
dump2polarion/utils.py
dump2polarion/verify.py
dump2polarion/xunit_exporter.py
dump2polarion/exporters/__init__.py
dump2polarion/exporters/requirements_exporter.py
dump2polarion/exporters/testcases_exporter.py
dump2polarion/exporters/transform.py
dump2polarion/exporters/transform_projects.py
dump2polarion/exporters/verdicts.py
dump2polarion/exporters/xunit_exporter.py
dump2polarion/results/__init__.py
dump2polarion/results/csvtools.py
dump2polarion/results/dbtools.py
dump2polarion/results/importer.py
dump2polarion/results/jsontools.py
dump2polarion/results/junittools.py
dump2polarion/results/ostriztools.py
dump2polarion-0.48.0.dist-info/LICENCE.txt
dump2polarion-0.48.0.dist-info/METADATA
dump2polarion-0.48.0.dist-info/WHEEL
dump2polarion-0.48.0.dist-info/entry_points.txt
dump2polarion-0.48.0.dist-info/top_level.txt
dump2polarion-0.48.0.dist-info/RECORD
