Metadata-Version: 2.1
Name: dump2polarion
Version: 0.48.0
Summary: Dump testcases results to xunit file; submit files to Polarion Importers
Home-page: https://github.com/mkoura/dump2polarion
Author: Martin Kourim
Author-email: mkourim@redhat.com
License: GPL
Keywords: polarion,testing
Platform: UNKNOWN
Classifier: Development Status :: 3 - Alpha
Classifier: Topic :: Software Development :: Libraries :: Python Modules
Classifier: Topic :: Software Development :: Testing
Classifier: License :: OSI Approved :: GNU General Public License v2 (GPLv2)
Classifier: Programming Language :: Python :: 3.5
Classifier: Programming Language :: Python :: 3.6
Classifier: Programming Language :: Python :: 3.7
Classifier: Intended Audience :: Developers
Requires-Dist: lxml
Requires-Dist: pyyaml
Requires-Dist: requests
Requires-Dist: docutils
Requires-Dist: packaging
Requires-Dist: python-box
Requires-Dist: polarion-tools-common
